{
  "formatVersion": 1,
  "database": {
    "version": 1,
    "identityHash": "13b0b95628c75c880f25043d2149f625",
    "entities": [
      {
        "tableName": "device_step_counter",
        "createSql": "CREATE TABLE IF NOT EXISTS `${TABLE_NAME}` (`id` INTEGER PRIMARY KEY AUTOINCREMENT, `stepNum` INTEGER NOT NULL, `dayAt` INTEGER NOT NULL)",
        "fields": [
          {
            "fieldPath": "id",
            "columnName": "id",
            "affinity": "INTEGER",
            "notNull": false
          },
          {
            "fieldPath": "stepNum",
            "columnName": "stepNum",
            "affinity": "INTEGER",
            "notNull": true
          },
          {
            "fieldPath": "dayAt",
            "columnName": "dayAt",
            "affinity": "INTEGER",
            "notNull": true
          }
        ],
        "primaryKey": {
          "columnNames": [
            "id"
          ],
          "autoGenerate": true
        },
        "indices": [],
        "foreignKeys": []
      }
    ],
    "views": [],
    "setupQueries": [
      "CREATE TABLE IF NOT EXISTS room_master_table (id INTEGER PRIMARY KEY,identity_hash TEXT)",
      "INSERT OR REPLACE INTO room_master_table (id,identity_hash) VALUES(42, '13b0b95628c75c880f25043d2149f625')"
    ]
  }
}